revertex/__init__.py
revertex/_version.py
revertex/cli.py
revertex/core.py
revertex/plot.py
revertex/utils.py
revertex/generators/__init__.py
revertex/generators/beta.py
revertex/generators/borehole.py
revertex/generators/shell.py
revertex/generators/surface.py
revertex-0.2.0.dist-info/licenses/LICENSE
revertex-0.2.0.dist-info/METADATA
revertex-0.2.0.dist-info/WHEEL
revertex-0.2.0.dist-info/entry_points.txt
revertex-0.2.0.dist-info/top_level.txt
revertex-0.2.0.dist-info/RECORD
