Metadata-Version: 2.4
Name: revertex
Version: 0.2.0
Summary: Generate Geant4 event vertices in Python
Author-email: Luigi Pertoldi <gipert@pm.me>
Maintainer: The LEGEND Collaboration
License-Expression: GPL-3.0
Project-URL: Homepage, https://github.com/legend-exp/revertex
Project-URL: Bug Tracker, https://github.com/legend-exp/revertex/issues
Project-URL: Discussions, https://github.com/legend-exp/revertex/discussions
Project-URL: Changelog, https://github.com/legend-exp/revertex/releases
Classifier: Intended Audience :: Developers
Classifier: Intended Audience :: Science/Research
Classifier: Operating System :: MacOS
Classifier: Operating System :: POSIX
Classifier: Operating System :: Unix
Classifier: Programming Language :: Python
Classifier: Programming Language :: Python :: 3
Classifier: Programming Language :: Python :: 3 :: Only
Classifier: Topic :: Scientific/Engineering
Requires-Python: >=3.10
License-File: LICENSE
Requires-Dist: pyg4ometry
Requires-Dist: hist
Requires-Dist: scipy
Requires-Dist: numpy
Requires-Dist: awkward
Requires-Dist: legend-pydataobj>=1.11.6
Requires-Dist: legend-pygeom-hpges>=0.9.0
Requires-Dist: legend-pygeom-tools>=0.0.25
Requires-Dist: reboost
Requires-Dist: dbetto
Requires-Dist: matplotlib
Provides-Extra: all
Requires-Dist: revertex[docs,test]; extra == "all"
Provides-Extra: docs
Requires-Dist: furo; extra == "docs"
Requires-Dist: myst-parser; extra == "docs"
Requires-Dist: sphinx; extra == "docs"
Requires-Dist: sphinx-copybutton; extra == "docs"
Provides-Extra: test
Requires-Dist: pre-commit; extra == "test"
Requires-Dist: pylegendtestdata; extra == "test"
Requires-Dist: pytest>=6.0; extra == "test"
Requires-Dist: pytest-cov; extra == "test"
Dynamic: license-file
